assignment11Luke/__init__.py
assignment11Luke/sentiment.py
assignment11Luke-0.0.1.dist-info/METADATA
assignment11Luke-0.0.1.dist-info/WHEEL
assignment11Luke-0.0.1.dist-info/top_level.txt
assignment11Luke-0.0.1.dist-info/RECORD
