Metadata-Version: 2.1
Name: assignment11Luke
Version: 0.0.1
Summary: Luke Twitter Sentiment
Home-page: UNKNOWN
Author: Luke Cunningham
Author-email: lcunnin2@g.emporia.edu
License: UNKNOWN
Keywords: python,first package
Platform: UNKNOWN
Classifier: Development Status :: 3 - Alpha
Classifier: Intended Audience :: Education
Classifier: Programming Language :: Python :: 2
Classifier: Programming Language :: Python :: 3
Classifier: Operating System :: MacOS :: MacOS X
Classifier: Operating System :: Microsoft :: Windows
Requires-Dist: textblob
Requires-Dist: pandas
